{
  "name": "Obstacle Pressure",
  "seed": 20260523,
  "pipelineKind": "neural",
  "initialBrainKind": "explorerForager",
  "brainHiddenNodeCount": 4,
  "enableBiomes": true,
  "biomeMapKind": "verticalEdgeLadderBands",
  "enableObstacles": true,
  "obstacleMapKind": "verticalBarrierWithGaps",
  "obstacleCellSize": 320,
  "worldWidth": 8000,
  "worldHeight": 5000,
  "biomeCellSize": 1000,
  "resourceVoidBorderWidth": 320,
  "fixedDeltaSeconds": 0.033333335,
  "spatialCellSize": 64,
  "worldSenseIntervalTicks": 10,
  "enableSectorVision": true,
  "statsSnapshotIntervalTicks": 300,
  "initialCreatureCount": 100,
  "initialCreatureSpawnRegion": "leftThird",
  "initialResourcesPerMillionArea": 18.5,
  "initialCreatureEnergyMin": 65,
  "initialCreatureEnergyMax": 110,
  "resourceRadiusMin": 3,
  "resourceRadiusMax": 8,
  "resourceCaloriesMin": 55,
  "resourceCaloriesMax": 120,
  "resourceMaxCalories": 120,
  "resourceRegrowthMin": 0.22,
  "resourceRegrowthMax": 1.1,
  "relocateDepletedResources": true,
  "plantRespawnDelaySecondsMin": 110,
  "plantRespawnDelaySecondsMax": 340,
  "resourceClusterStrength": 0.26,
  "resourceClusterRadius": 700,
  "plantLocalDispersalChance": 0.35,
  "plantLocalDispersalRadius": 780,
  "enableLocalFertility": true,
  "localFertilityCellSize": 500,
  "localFertilityMinimumMultiplier": 0.35,
  "localFertilityRecoveryPerSecond": 0.0003,
  "localFertilityDepletionPerPlant": 0.12,
  "localFertilityNeighborDepletionShare": 0.55,
  "basalEnergyPerSecond": 0.17,
  "movementEnergyPerSecond": 0.26,
  "movementSpeedCostExponent": 1.6,
  "eatCaloriesPerSecond": 18,
  "gutCapacityCalories": 55,
  "digestionCaloriesPerSecond": 5,
  "reproductionEnergyThreshold": 130,
  "offspringEnergyInvestment": 44,
  "eggProductionEnergyPerSecond": 1.25,
  "eggIncubationSeconds": 34,
  "maturityAgeSeconds": 160,
  "reproductionCooldownSeconds": 45,
  "requireReproductionIntent": true,
  "reproductivePrimeAgeSeconds": 420,
  "reproductiveSenescenceAgeSeconds": 1500,
  "senescentFertilityMultiplier": 0.18,
  "crowdingFertilityPenalty": 0.65,
  "dietaryAdaptation": 0.1,
  "carrionAdaptation": 0,
  "biteStrength": 0.55,
  "damageResistance": 1,
  "mutationStrength": 0.06,
  "traitMutationRate": 0.2,
  "brainMutationRate": 0.08
}
